<?xml version="1.0" encoding="utf-8" ?>
<dwsync>
<file name="font-awesome.min.css" server="yzuhc3.ddns.net" local="130479847840000000" remote="130819580400000000" />
<file name="style.css" server="yzuhc3.ddns.net" local="130732486840000000" remote="130819580400000000" />
<file name="responsive.css" server="yzuhc3.ddns.net" local="130536089640000000" remote="130819580400000000" />
<file name="animate.css" server="yzuhc3.ddns.net" local="130361349080000000" remote="130819580400000000" />
<file name="font-awesome.css" server="yzuhc3.ddns.net" local="130479847840000000" remote="130819581000000000" />
<file name="font-awesome.min.css" server="ftp.clouds.twgogo.org" local="130479847840000000" remote="130837089600000000" />
<file name="style.css" server="ftp.clouds.twgogo.org" local="130732486840000000" remote="130837089600000000" />
<file name="responsive.css" server="ftp.clouds.twgogo.org" local="130536089640000000" remote="130837092000000000" />
<file name="animate.css" server="ftp.clouds.twgogo.org" local="130361349080000000" remote="130837093200000000" />
<file name="font-awesome.css" server="ftp.clouds.twgogo.org" local="130479847840000000" remote="130837093200000000" />
</dwsync>